sd212review/__init__.py
sd212review/whichunit.py
sd212review-0.0.24.dist-info/LICENSE
sd212review-0.0.24.dist-info/METADATA
sd212review-0.0.24.dist-info/WHEEL
sd212review-0.0.24.dist-info/top_level.txt
sd212review-0.0.24.dist-info/RECORD
