Metadata-Version: 2.1
Name: sd212review
Version: 0.0.24
Summary: Simple Python module to tell you which unit to write review questions for SD212
Author-email: Dan Roche <roche@usna.edu>
Project-URL: Homepage, https://github.com/sd212usna/sd212review
Requires-Python: >=3.10
License-File: LICENSE
